{"items": [
  {
    "sku": "IB1251",
    "name": "One India Girl",
    "category": "Book",
    "type": "Novel",
    "publisher": "Oxford",
    "bestseller": "No",
    "language": "English",
    "author": "Chetan Bhagat",
    "price": 256.98,
    "year": "2006",
    "description": "Romantic story"
  },
  {
    "sku": "IB1252",
    "name": "The Great Gatsby",
    "category": "Book",
    "type": "Novel",
    "publisher": "Olympia",
    "bestseller": "Yes",
    "language": "English, French",
    "author": "Fitzgerald, F. Scott",
    "price": 356.28,
    "year": "2009",
    "description": "Suspense and drama"
  },
  {
    "sku": "IB1253",
    "name": "A Passage to India",
    "category": "Book",
    "type": "Novel",
    "publisher": "Oxford",
    "bestseller": "yes",
    "language": "English, French",
    "author": "E. M. Forster",
    "price": 175.21,
    "year": "1924",
    "description": "Indian history and culture"
  },
  {
    "sku": "IB1254",
    "name": "The birth Of Europe",
    "category": "Book",
    "type": "Novel",
    "publisher": "Wiley-Blackwell",
    "bestseller": "yes",
    "language": "English, French",
    "author": "Jacques Le Goff",
    "price": 265.5,
    "year": "2016",
    "description": "Europian history and culture"
  },
  {
    "sku": "IB1255",
    "name": "Firearms:An Illustrated History",
    "category": "Book",
    "type": "Novel",
    "publisher": "DK",
    "bestseller": "yes",
    "language": "English, French",
    "author": "Fitzgerald, F.",
    "price": 1694,
    "year": "2004",
    "description": "Indian history and culture"
  },
  {
    "sku": "IB1256",
    "name": "The Marble Collector",
    "category": "Book",
    "type": "Novel",
    "publisher": "HarperCollins",
    "bestseller": "yes",
    "language": "English, French",
    "author": "Fitzgerald, F.",
    "price": 1505,
    "year": "2015",
    "description": "A forgotten Childhood"
  },
  {
    "sku": "IB1257",
    "name": "The 48 Laws Of Power (The Robert Greene Collection)",
    "category": "Book",
    "type": "Novel",
    "publisher": "Oxford",
    "bestseller": "yes",
    "language": "English, French",
    "author": "Fitzgerald, F.",
    "price": 358,
    "year": "2006",
    "description": "The Robert Greene Collection"
  },
  {
    "sku": "IB1258",
    "name": "Hardcover",
    "category": "Book",
    "type": "Novel",
    "publisher": "Oxford",
    "bestseller": "yes",
    "language": "English, French",
    "author": "Fitzgerald, F.",
    "price": 1567,
    "year": "2006",
    "description": "Indian history and culture"
  },
  {
    "sku": "IB1259",
    "name": "Good To Great: Why Some Companies Make the Leap...And Others Don't",
    "category": "Book",
    "type": "Novel",
    "publisher": "Oxford",
    "bestseller": "yes",
    "language": "English, French",
    "author": "Fitzgerald, F.",
    "price": 999,
    "year": "2006",
    "description": "Corporate details and politics"
  },
  {
    "sku": "IB1260",
    "name": "Jack and Jill",
    "category": "Book",
    "type": "Novel",
    "publisher": "Oxford",
    "bestseller": "yes",
    "language": "English, French",
    "author": "Karan Verma",
    "price": 243,
    "year": "2009",
    "description": "Good To Great"
  },
  {
    "sku": "IB1261",
    "name": "Midnight's Children",
    "category": "Book",
    "type": "Novel",
    "publisher": "Oxford",
    "bestseller": "yes",
    "language": "English, French",
    "author": "Fitzgerald, F.",
    "price": 499,
    "year": "2006",
    "description": "Edeucational Deatails"
  },
  {
    "sku": "IB1262",
    "name": "Long Walk To Freedom",
    "category": "Book",
    "type": "Management",
    "publisher": "Oxford",
    "bestseller": "yes",
    "language": "English, French",
    "author": "Felson Mandela ",
    "price": 699,
    "year": "2006",
    "description": "Long Walk To Freedom"
  },
  {
    "sku": "IB1263",
    "name": "Uglies (Uglies Trilogy)",
    "category": "Book",
    "type": "Novel",
    "publisher": "Oxford",
    "bestseller": "yes",
    "language": "English, French",
    "author": "Felson Mandela ",
    "price": 1289,
    "year": "2006",
    "description": "This exciting story makes you realise how important it is not to judge people by appearances."
  },
  {
    "sku": "IB1264",
    "name": "The Moon Is a Harsh Mistress",
    "category": "Book",
    "type": "Novel",
    "publisher": "Oxford",
    "bestseller": "yes",
    "language": "English, French",
    "author": "Felson Mandela ",
    "price": 639,
    "year": "2006",
    "description": "Indian history and culture"
  },
  {
    "sku": "IB1265",
    "name": "Second-Hand Time",
    "category": "Book",
    "type": "Novel",
    "publisher": "Oxford",
    "bestseller": "yes",
    "language": "English, French",
    "author": "Felson Mandela ",
    "price": 2990,
    "year": "2006",
    "description": "Indian history and culture"
  },
  {
    "sku": "IB1266",
    "name": "A Song of Ice and Fire - A Game of Thrones",
    "category": "Book",
    "type": "Novel",
    "publisher": "Oxford",
    "bestseller": "yes",
    "language": "English, French",
    "author": "George R.R. Martin ",
    "price": 4199,
    "year": "2006",
    "description": "Indian history and culture"
  },
  {
    "sku": "IB1267",
    "name": "The Sandman: Preludes & Nocturnes ",
    "category": "Book",
    "type": "Management",
    "publisher": "Oxford",
    "bestseller": "yes",
    "language": "English, French",
    "author": "Felson Mandela ",
    "price": 9863,
    "year": "2006",
    "description": "IManagement Details and planning"
  },
  {
    "sku": "IB1268",
    "name": "The Blind Assassin",
    "category": "Book",
    "type": "Novel",
    "publisher": "Bloomsbury Publishing PLC; Special edition edition (2 November 2009)",
    "bestseller": "yes",
    "language": "English, French",
    "author": "Margaret Atwood ",
    "price": 2500,
    "year": "2006",
    "description": "Indian history and culture"
  },
  {
    "sku": "IB1269",
    "name": "Stardust",
    "category": "Book",
    "type": "Novel",
    "publisher": "Headline Review (6 January 2000)",
    "bestseller": "yes",
    "language": "English, French",
    "author": "Neil Gaiman",
    "price": 2355,
    "year": "2006",
    "description": "Indian history and culture"
  },
  {
    "sku": "IB1270",
    "name": "Woman on the Edge of Time: The classic feminist dystopian novel",
    "category": "Book",
    "type": "Novel",
    "publisher": "Del Rey (11 August 2016)",
    "bestseller": "yes",
    "language": "English, French",
    "author": "Marge Piercy",
    "price": 2245,
    "year": "2006",
    "description": "Indian history and culture"
  },
  {
    "sku": "IB1271",
    "name": "The Ender Quartet Boxed Set: Ender's Game, Speaker for the Dead, Xenocide, Children of the Mind (The Ender Quintet)",
    "category": "Book",
    "type": "Management",
    "publisher": "Tor Science Fiction; Box edition (4 November 2008)",
    "bestseller": "yes",
    "language": "English, French",
    "author": "Card lives",
    "price": 2404,
    "year": "2006",
    "description": "Indian history and culture"
  },
  {
    "sku": "IB1272",
    "name": "Woman on the Edge of Time: The classic feminist dystopian novel",
    "category": "Book",
    "type": "Novel",
    "publisher": "Del Rey (11 August 2016)",
    "bestseller": "yes",
    "language": "English, French",
    "author": "Marge Piercy",
    "price": 2245,
    "year": "2006",
    "description": "Indian history and culture"
  },
  {
    "sku": "IB1273",
    "name": "Think and Grow Rich",
    "category": "Book",
    "type": "Novel",
    "publisher": "Amazing Reads (1 January 2014)",
    "bestseller": "yes",
    "language": "English, French",
    "author": "Napoleon Hill",
    "price": 199,
    "year": "2006",
    "description": "Peronality Development"
  },
  {
    "sku": "IB1274",
    "name": "The Immortals of Meluha (Shiva Trilogy)",
    "category": "Book",
    "type": "Novel",
    "publisher": "Westland; Latest Edition edition (24 July 2017)",
    "bestseller": "yes",
    "language": "English, French",
    "author": "Amish ",
    "price": 234,
    "year": "2006",
    "description": "Mythologies"
  },
  {
    "sku": "IB1275",
    "name": "Malgudi Adventures",
    "category": "Book",
    "type": "Novel",
    "publisher": "Del Rey (11 August 2016)",
    "bestseller": "yes",
    "language": "English, French",
    "author": "Marge Piercy",
    "price": 250,
    "year": "2006",
    "description": "Comedy and drama"
  },
  {
    "sku": "IB1276",
    "name": "Train to Pakistan",
    "category": "Book",
    "type": "Novel",
    "publisher": "Del Rey (11 August 2016)",
    "bestseller": "yes",
    "language": "English, French",
    "author": "Marge Piercy",
    "price": 199,
    "year": "2006",
    "description": "Documentroy"
  },
  {
    "sku": "IB1277",
    "name": "My Gita",
    "category": "Book",
    "type": "Novel",
    "publisher": "Del Rey (11 August 2016)",
    "bestseller": "yes",
    "language": "English, French",
    "author": "Marge Piercy",
    "price": 295,
    "year": "2006",
    "description": "Indian history and culture"
  },
  {
    "sku": "IB1278",
    "name": "Elon Musk",
    "category": "Book",
    "type": "Science Fiction",
    "publisher": "Del Rey (11 August 2016)",
    "bestseller": "yes",
    "language": "English, French",
    "author": "Marge Piercy",
    "price": 699,
    "year": "2016",
    "description": "Science and technology"
  }
]}